dexie.py
dexie_py-0.1.0.dist-info/METADATA
dexie_py-0.1.0.dist-info/WHEEL
dexie_py-0.1.0.dist-info/licenses/LICENSE
dexie_py-0.1.0.dist-info/RECORD
