Metadata-Version: 2.1
Name: dexie.py
Version: 0.1.0
Summary: A simple Dexie.Space API client
Project-URL: Homepage, https://github.com/yyolk/dexie.py
Project-URL: Bug Tracker, https://github.com/yyolk/dexie.py/issues
Author-email: Joseph Chiocchi <joe@yolk.cc>
License-File: LICENSE
Classifier: Intended Audience :: Developers
Classifier: License :: OSI Approved :: MIT License
Classifier: Operating System :: OS Independent
Classifier: Programming Language :: Python :: 3
Classifier: Programming Language :: Python :: 3 :: Only
Classifier: Programming Language :: Python :: 3.10
Classifier: Programming Language :: Python :: 3.11
Requires-Python: >=3.10
Requires-Dist: base58
Requires-Dist: uplink
